btcat/__init__.py
btcat/__main__.py
btcat/pytransform/__init__.py
btcat/pytransform/platforms/linux/aarch64/_pytransform.so
btcat/pytransform/platforms/linux/x86_64/_pytransform.so
btcat-0.0.1.dist-info/LICENSE.txt
btcat-0.0.1.dist-info/METADATA
btcat-0.0.1.dist-info/WHEEL
btcat-0.0.1.dist-info/top_level.txt
btcat-0.0.1.dist-info/RECORD
